README.md
phylodeep_data_bd/__init__.py
phylodeep_data_bd/large/CNN_FULL_TREE.csv.xz
phylodeep_data_bd/large/FFNN_SUMSTATS.csv.xz
phylodeep_data_bd/large/target.csv.xz
phylodeep_data_bd/small/CNN_FULL_TREE.csv.xz
phylodeep_data_bd/small/FFNN_SUMSTATS.csv.xz
phylodeep_data_bd/small/target.csv.xz
phylodeep_data_bd-0.6.dist-info/LICENSE
phylodeep_data_bd-0.6.dist-info/METADATA
phylodeep_data_bd-0.6.dist-info/WHEEL
phylodeep_data_bd-0.6.dist-info/entry_points.txt
phylodeep_data_bd-0.6.dist-info/top_level.txt
phylodeep_data_bd-0.6.dist-info/RECORD
